{"version":1,"resource":"file:///home/quangthaictc/.config/swaync/style.css","entries":[{"id":"ZG4n.css","timestamp":1747970299559},{"id":"KgQX.css","timestamp":1747970371488},{"id":"zW5F.css","timestamp":1747970473242},{"id":"8mrw.css","timestamp":1747970528632},{"id":"CJgb.css","timestamp":1747970581824},{"id":"IjJM.css","timestamp":1747970643156},{"id":"uI22.css","timestamp":1747970692478},{"id":"GzZD.css","timestamp":1747970733491},{"id":"CoKG.css","timestamp":1747970748705},{"id":"7oaV.css","timestamp":1747970877653},{"id":"0L5A.css","timestamp":1747970973120},{"id":"UIJk.css","timestamp":1747971125734},{"id":"TVsB.css","timestamp":1747971233698},{"id":"1l1L.css","timestamp":1747971591568},{"id":"oKYj.css","timestamp":1747971632068},{"id":"HOV9.css","timestamp":1747971653198},{"id":"4az9.css","timestamp":1747971672417},{"id":"0DR1.css","source":"undoRedo.source","timestamp":1747971719176},{"id":"Jrzw.css","timestamp":1747971747779},{"id":"M57F.css","timestamp":1747971819599},{"id":"Lq4R.css","timestamp":1747971879482},{"id":"7aIh.css","timestamp":1747971917927},{"id":"koxZ.css","timestamp":1747971946582},{"id":"9YAy.css","timestamp":1747971960330}]}